webtop/__init__.py
web_top-0.1.2.dist-info/WHEEL
web_top-0.1.2.dist-info/METADATA
web_top-0.1.2.dist-info/RECORD
