Metadata-Version: 2.1
Name: web-top
Version: 0.1.2
Summary: web-top is a UNIX top-like tool to live HTTP requests and responses of any web server.
Home-page: https://top-framework.readthedocs.io/en/latest/web-top/index.html
License: MIT
Keywords: cli,UNIX,TUI,Gunicorn,WSGI
Author: Mikko Ohtamaa
Author-email: mikko@opensourcehacker.com
Requires-Python: >=3.9,<4.0
Classifier: License :: OSI Approved :: MIT License
Classifier: Programming Language :: Python :: 3
Classifier: Programming Language :: Python :: 3.10
Classifier: Programming Language :: Python :: 3.9
Requires-Dist: top-framework (>=0.1.1,<0.2.0)
Project-URL: Repository, https://github.com/tradingstrategy-ai/web-top
